pyfutugrpc/__init__.py
pyfutugrpc/accinfo_pb2.py
pyfutugrpc/accinfo_pb2.pyi
pyfutugrpc/accinfo_pb2_grpc.py
pyfutugrpc/acct_pb2.py
pyfutugrpc/acct_pb2.pyi
pyfutugrpc/acct_pb2_grpc.py
pyfutugrpc/deal_pb2.py
pyfutugrpc/deal_pb2.pyi
pyfutugrpc/deal_pb2_grpc.py
pyfutugrpc/futuapi_pb2.py
pyfutugrpc/futuapi_pb2.pyi
pyfutugrpc/futuapi_pb2_grpc.py
pyfutugrpc/kline_pb2.py
pyfutugrpc/kline_pb2.pyi
pyfutugrpc/kline_pb2_grpc.py
pyfutugrpc/order_pb2.py
pyfutugrpc/order_pb2.pyi
pyfutugrpc/order_pb2_grpc.py
pyfutugrpc/orderbook_pb2.py
pyfutugrpc/orderbook_pb2.pyi
pyfutugrpc/orderbook_pb2_grpc.py
pyfutugrpc/orderfee_pb2.py
pyfutugrpc/orderfee_pb2.pyi
pyfutugrpc/orderfee_pb2_grpc.py
pyfutugrpc/position_pb2.py
pyfutugrpc/position_pb2.pyi
pyfutugrpc/position_pb2_grpc.py
pyfutugrpc/rtdata_pb2.py
pyfutugrpc/rtdata_pb2.pyi
pyfutugrpc/rtdata_pb2_grpc.py
pyfutugrpc/seqquote_pb2.py
pyfutugrpc/seqquote_pb2.pyi
pyfutugrpc/seqquote_pb2_grpc.py
pyfutugrpc/stockquote_pb2.py
pyfutugrpc/stockquote_pb2.pyi
pyfutugrpc/stockquote_pb2_grpc.py
pyfutugrpc/stocksnapshot_pb2.py
pyfutugrpc/stocksnapshot_pb2.pyi
pyfutugrpc/stocksnapshot_pb2_grpc.py
pyfutugrpc-0.1.dist-info/METADATA
pyfutugrpc-0.1.dist-info/WHEEL
pyfutugrpc-0.1.dist-info/top_level.txt
pyfutugrpc-0.1.dist-info/RECORD
